README.md
setup.cfg
setup.py
fossor/__init__.py
fossor/cli.py
fossor/engine.py
fossor/plugin.py
fossor.egg-info/PKG-INFO
fossor.egg-info/SOURCES.txt
fossor.egg-info/dependency_links.txt
fossor.egg-info/entry_points.txt
fossor.egg-info/requires.txt
fossor.egg-info/top_level.txt
fossor/checks/__init__.py
fossor/checks/buddyinfo.py
fossor/checks/check.py
fossor/checks/diskusage.py
fossor/checks/dmesg.py
fossor/checks/examplecheck.py
fossor/checks/listvariables.py
fossor/checks/loadavg.py
fossor/checks/memusage.py
fossor/checks/netiface_errors.py
fossor/checks/other_users.py
fossor/checks/raid_status.py
fossor/checks/similar_log_errors.py
fossor/checks/system_log_volume.py
fossor/checks/thcount.py
fossor/reports/__init__.py
fossor/reports/dict_object_report.py
fossor/reports/json.py
fossor/reports/report.py
fossor/reports/stdout.py
fossor/utils/__init__.py
fossor/utils/anomaly_detection.py
fossor/utils/filetools.py
fossor/utils/misc.py
fossor/variables/__init__.py
fossor/variables/examplevariable.py
fossor/variables/hostname.py
fossor/variables/logfiles.py
fossor/variables/other_users.py
fossor/variables/pid.py
fossor/variables/terminal_size.py
fossor/variables/variable.py
test/__init__.py
test/test_check_buddyinfo.py
test/test_check_disk_usage.py
test/test_check_dmesg.py
test/test_check_listvariables.py
test/test_check_memusage.py
test/test_check_netiface_errors.py
test/test_check_other_users.py
test/test_check_similar_log_errors.py
test/test_check_thcount.py
test/test_cli.py
test/test_fossor.py
test/test_plugin_import.py
test/test_plugin_multiprocessing.py
test/test_plugin_notification.py
test/test_plugin_process_cleanup.py
test/test_report.py
test/test_report_json.py
test/test_style.py
test/test_utils_anomaly_detection.py
test/test_utils_filetools.py
test/test_utils_misc.py
test/test_variable_other_users.py