Metadata-Version: 1.1
Name: fossor
Version: 1.1.0
Summary: A plugin oriented tool for automating the investigation of broken hosts and services.
Home-page: https://github.com/linkedin/fossor
Author: Steven R. Callister
Author-email: scallist@linkedin.com
License: License :: OSI Approved :: BSD License
Platform: UNKNOWN
Classifier: Development Status :: 5 - Production/Stable
Classifier: Environment :: Console
Classifier: Intended Audience :: Developers
Classifier: Intended Audience :: Information Technology
Classifier: Intended Audience :: System Administrators
Classifier: License :: OSI Approved :: BSD License
Classifier: Programming Language :: Python :: 3.6
Classifier: Programming Language :: Python :: 3 :: Only
Classifier: Operating System :: POSIX :: Linux
